LICENSE
README.md
setup.cfg
setup.py
irrhound/__init__.py
irrhound/irrhound.py
irrhound.egg-info/PKG-INFO
irrhound.egg-info/SOURCES.txt
irrhound.egg-info/dependency_links.txt
irrhound.egg-info/requires.txt
irrhound.egg-info/top_level.txt
irrhound/shared/__init__.py
irrhound/shared/irr_scan.py
irrhound/shared/irr_source_list.py
irrhound/shared/peer.py
irrhound/shared/route_object.py
irrhound/shared/whois_proxy.py
tests/__init__.py
tests/test_scan.py
tests/test_whois.py