Metadata-Version: 2.1
Name: irrhound
Version: 1.2.2
Summary: A package to check for IRR resources
Home-page: https://github.com/vajra77/IRRHound
Author: Francesco Ferreri
Author-email: f.ferreri@namex.it
License: UNKNOWN
Platform: UNKNOWN
Classifier: Development Status :: 4 - Beta
Classifier: Intended Audience :: Developers
Classifier: License :: CC0 1.0 Universal (CC0 1.0) Public Domain Dedication
Classifier: Programming Language :: Python :: 3.8
